smflow/__init__.py
smflow/__main__.py
smflow/cli.py
smflow/cmd.py
smflow/hooks.py
smflow/install.py
smflow-0.3.8.dist-info/METADATA
smflow-0.3.8.dist-info/WHEEL
smflow-0.3.8.dist-info/entry_points.txt
smflow-0.3.8.dist-info/licenses/LICENSE
smflow-0.3.8.dist-info/RECORD
