Metadata-Version: 2.4
Name: smflow
Version: 0.3.8
Summary: Tools and git hooks to make it easier to work with submodules that are updated frequently.
Project-URL: Homepage, https://github.com/h0uter/smflow
Author-email: "W. Meijer" <houterm@gmail.com>
License-File: LICENSE
Keywords: git,git-hooks,git-submodule,git-submodules,hooks,multi-git,multi-repo,repo management,submodule,virtual-mono-repo
Classifier: Environment :: Console
Classifier: Intended Audience :: Developers
Classifier: License :: OSI Approved :: Apache Software License
Classifier: Operating System :: OS Independent
Classifier: Programming Language :: Python
Classifier: Programming Language :: Python :: 3 :: Only
Classifier: Programming Language :: Python :: 3.10
Classifier: Programming Language :: Python :: 3.11
Classifier: Programming Language :: Python :: 3.12
Classifier: Programming Language :: Python :: 3.13
Classifier: Topic :: Software Development :: Libraries
Requires-Python: >=3.10
Requires-Dist: gitpython>=3.1.44
Requires-Dist: uv>=0.7.8
